pelican_git/__init__.py
pelican_git/plugin.py
pelican_git/test_plugin.py
pelican_git/templates/git.jinja.html
pelican_git-0.1.13.dist-info/LICENSE
pelican_git-0.1.13.dist-info/METADATA
pelican_git-0.1.13.dist-info/WHEEL
pelican_git-0.1.13.dist-info/top_level.txt
pelican_git-0.1.13.dist-info/RECORD
