Metadata-Version: 2.1
Name: pelican-git
Version: 0.1.13
Summary: Easily embed Github files in your Pelican articles.
Home-page: https://github.com/minhhh/pelican_git
Author: Ha.Minh
Author-email: minhhh@minhhuyha.info
License: MIT
Platform: UNKNOWN
Classifier: Development Status :: 5 - Production/Stable
Classifier: Environment :: Console
Classifier: Intended Audience :: Developers
Classifier: License :: OSI Approved :: MIT License
Classifier: Natural Language :: English
Classifier: Operating System :: OS Independent
Classifier: Programming Language :: Python
Classifier: Programming Language :: Python :: 2.7
Classifier: Programming Language :: Python :: 3.6
Classifier: Programming Language :: Python :: 3.7
Classifier: Topic :: Internet :: WWW/HTTP
Classifier: Topic :: Software Development :: Libraries :: Python Modules
Classifier: Topic :: Text Processing
Requires-Python: >=2.7, !=3.0.*, !=3.1.*, !=3.2.*, !=3.3.*
Requires-Dist: setuptools
Requires-Dist: requests (>=2.2.0)
Requires-Dist: beautifulsoup4
Requires-Dist: jinja2
